tickerstore/__init__.py
tickerstore/daemon.py
tickerstore/errors.py
tickerstore/store.py
tickerstore/tempserver.py
TickerStore-0.0.8.dist-info/LICENSE
TickerStore-0.0.8.dist-info/METADATA
TickerStore-0.0.8.dist-info/WHEEL
TickerStore-0.0.8.dist-info/top_level.txt
TickerStore-0.0.8.dist-info/RECORD
