Metadata-Version: 2.1
Name: TickerStore
Version: 0.0.8
Summary: Historical data of financial instruments from NSE
Home-page: https://github.com/meticulousCraftman/tickerstore
Author: Apoorva Singh
Author-email: apoorva.singh157@gmail.com
License: MIT
Platform: UNKNOWN
Classifier: Programming Language :: Python :: 3
Classifier: License :: OSI Approved :: MIT License
Classifier: Operating System :: OS Independent
Requires-Dist: upstox
Requires-Dist: python-dotenv
Requires-Dist: Flask
Requires-Dist: influxdb
Requires-Dist: crayons
Requires-Dist: nsepy
Requires-Dist: pandas
Requires-Dist: requests
Requires-Dist: lxml
Requires-Dist: loguru
